basic_text_effects/__init__.py
basic_text_effects/basic_text_effects.py
basic_text_effects-0.0.4.dist-info/LICENSE
basic_text_effects-0.0.4.dist-info/METADATA
basic_text_effects-0.0.4.dist-info/WHEEL
basic_text_effects-0.0.4.dist-info/top_level.txt
basic_text_effects-0.0.4.dist-info/RECORD
